ScriptsOfTribute/Server.py
ScriptsOfTribute/__init__.py
ScriptsOfTribute/base_ai.py
ScriptsOfTribute/board.py
ScriptsOfTribute/enums.py
ScriptsOfTribute/game.py
ScriptsOfTribute/move.py
ScriptsOfTribute/runner.py
ScriptsOfTribute/Protos/__init__.py
ScriptsOfTribute/Protos/basics_pb2.py
ScriptsOfTribute/Protos/basics_pb2_grpc.py
ScriptsOfTribute/Protos/enums_pb2.py
ScriptsOfTribute/Protos/enums_pb2_grpc.py
ScriptsOfTribute/Protos/main_pb2.py
ScriptsOfTribute/Protos/main_pb2_grpc.py
scriptsoftribute-1.0.0.dist-info/LICENSE
scriptsoftribute-1.0.0.dist-info/METADATA
scriptsoftribute-1.0.0.dist-info/WHEEL
scriptsoftribute-1.0.0.dist-info/top_level.txt
scriptsoftribute-1.0.0.dist-info/RECORD
